src/__init__.py
src/__main__.py
src/main.py
src/models.py
src/todo.py
hackathon_cli_todo-0.1.0.dist-info/METADATA
hackathon_cli_todo-0.1.0.dist-info/WHEEL
hackathon_cli_todo-0.1.0.dist-info/entry_points.txt
hackathon_cli_todo-0.1.0.dist-info/licenses/LICENSE
hackathon_cli_todo-0.1.0.dist-info/RECORD
