Metadata-Version: 2.4
Name: hackathon-cli-todo
Version: 0.1.0
Summary: A simple, elegant command-line todo list application
Project-URL: Homepage, https://github.com/mussaratshamsher/HACKTHON-II-Todo-APP
Project-URL: Repository, https://github.com/mussaratshamsher/HACKTHON-II-Todo-APP
Project-URL: Issues, https://github.com/mussaratshamsher/HACKTHON-II-Todo-APP/issues
Author: Hackathon II Contributors
License: MIT
License-File: LICENSE
Keywords: cli,command-line,productivity,task-manager,todo
Classifier: Development Status :: 4 - Beta
Classifier: Intended Audience :: Developers
Classifier: Intended Audience :: End Users/Desktop
Classifier: License :: OSI Approved :: MIT License
Classifier: Operating System :: OS Independent
Classifier: Programming Language :: Python :: 3
Classifier: Programming Language :: Python :: 3.11
Classifier: Programming Language :: Python :: 3.12
Classifier: Programming Language :: Python :: 3.13
Classifier: Topic :: Office/Business :: Scheduling
Classifier: Topic :: Utilities
Requires-Python: >=3.11
Provides-Extra: dev
Requires-Dist: mypy>=1.0.0; extra == 'dev'
Requires-Dist: pytest-cov>=4.0.0; extra == 'dev'
Requires-Dist: pytest>=8.0.0; extra == 'dev'
Requires-Dist: ruff>=0.1.0; extra == 'dev'
